windowsha/__init__.py
windowsha-0.0.2.dist-info/METADATA
windowsha-0.0.2.dist-info/RECORD
windowsha-0.0.2.dist-info/WHEEL
windowsha-0.0.2.dist-info/top_level.txt
