Metadata-Version: 2.1
Name: windowsha
Version: 0.0.2
Summary: Parse Windows HA data to xlsx
Home-page: https://github.com/SanPersie
Author: Li Xingxuan
Author-email: lxx895466249@gmail.com
License: UNKNOWN
Platform: UNKNOWN
Classifier: Programming Language :: Python :: 3
Classifier: License :: OSI Approved :: MIT License
Classifier: Operating System :: OS Independent
